anvai_sdk/__init__.py
anvai_sdk/client.py
anvai_sdk/errors.py
anvai_sdk/py.typed
anvai_sdk/types.py
anvai_sdk/api/__init__.py
anvai_sdk/api/auth/__init__.py
anvai_sdk/api/auth/get_token.py
anvai_sdk/api/collections/__init__.py
anvai_sdk/api/collections/create_collection.py
anvai_sdk/api/collections/get_collections.py
anvai_sdk/api/insights/__init__.py
anvai_sdk/api/insights/create_insights.py
anvai_sdk/api/insights/get_insight_status_by_task_id.py
anvai_sdk/api/insights/get_summary.py
anvai_sdk/api/insights/search.py
anvai_sdk/models/__init__.py
anvai_sdk/models/create_collection_body.py
anvai_sdk/models/create_collection_response_200.py
anvai_sdk/models/create_collection_response_200_files_item.py
anvai_sdk/models/create_insights_body.py
anvai_sdk/models/create_insights_response_200.py
anvai_sdk/models/get_collections_response_200_item.py
anvai_sdk/models/get_collections_response_200_item_files_item.py
anvai_sdk/models/get_insight_status_by_task_id_response_200.py
anvai_sdk/models/get_summary_response_200.py
anvai_sdk/models/get_token_body.py
anvai_sdk/models/get_token_response_200.py
anvai_sdk/models/search_body.py
anvai_sdk/models/search_body_search_type.py
anvai_sdk/models/search_response_201.py
anvai_sdk/models/search_response_201_sentence_results_json.py
anvai_sdk/models/search_response_201_sentence_results_json_input_documents_item.py
anvai_sdk/models/search_response_201_sentence_results_json_input_documents_item_metadata.py
anvai_sdk-1.0.5.dist-info/METADATA
anvai_sdk-1.0.5.dist-info/WHEEL
anvai_sdk-1.0.5.dist-info/top_level.txt
anvai_sdk-1.0.5.dist-info/RECORD
