Metadata-Version: 2.2
Name: anvai-sdk
Version: 1.0.5
Summary: A client library for accessing Anvai python sdk
Requires-Python: >=3.9, <4
Requires-Dist: httpx<0.29.0,>=0.20.0
Requires-Dist: attrs>=22.2.0
Requires-Dist: python-dateutil<3,>=2.8.0
Dynamic: description
Dynamic: description-content-type
Dynamic: requires-dist
Dynamic: requires-python
Dynamic: summary
